blackmamba72_tgw/__init__.py
blackmamba72_tgw/py.typed
blackmamba72_tgw/_jsii/__init__.py
blackmamba72_tgw/_jsii/blackmamba72-tgw@0.0.2.jsii.tgz
blackmamba72_tgw-0.0.2.dist-info/LICENSE
blackmamba72_tgw-0.0.2.dist-info/METADATA
blackmamba72_tgw-0.0.2.dist-info/WHEEL
blackmamba72_tgw-0.0.2.dist-info/top_level.txt
blackmamba72_tgw-0.0.2.dist-info/RECORD
